djangocms_blog/__init__.py
djangocms_blog/apps.py
djangocms_blog/cms_appconfig.py
djangocms_blog/cms_config.py
djangocms_blog/fields.py
djangocms_blog/managers.py
djangocms_blog/models.py
djangocms_blog/settings.py
djangocms_blog/urls.py
djangocms_blog/migrations/0001_initial.py
djangocms_blog/migrations/0002_post_sites.py
djangocms_blog/migrations/0003_auto_20141201_2252.py
djangocms_blog/migrations/0004_auto_20150108_1435.py
djangocms_blog/migrations/0005_auto_20150212_1118.py
djangocms_blog/migrations/0006_auto_20150214_1907.py
djangocms_blog/migrations/0007_auto_20150719_0933.py
djangocms_blog/migrations/0008_auto_20150814_0831.py
djangocms_blog/migrations/0009_latestpostsplugin_tags_new.py
djangocms_blog/migrations/0010_auto_20150923_1151.py
djangocms_blog/migrations/0011_auto_20151024_1809.py
djangocms_blog/migrations/0012_auto_20151220_1734.py
djangocms_blog/migrations/0013_auto_20160201_2235.py
djangocms_blog/migrations/0014_auto_20160215_1331.py
djangocms_blog/migrations/0015_auto_20160408_1849.py
djangocms_blog/migrations/0016_auto_20160502_1741.py
djangocms_blog/migrations/0017_thumbnail_move.py
djangocms_blog/migrations/0018_thumbnail_move2.py
djangocms_blog/migrations/0019_thumbnail_move3.py
djangocms_blog/migrations/0020_thumbnail_move4.py
djangocms_blog/migrations/0021_auto_20160823_2008.py
djangocms_blog/migrations/0021_post_liveblog.py
djangocms_blog/migrations/0022_auto_20160605_2305.py
djangocms_blog/migrations/0022_auto_20170304_1040.py
djangocms_blog/migrations/0023_auto_20160626_1539.py
djangocms_blog/migrations/0024_auto_20160706_1524.py
djangocms_blog/migrations/0025_auto_20160803_0858.py
djangocms_blog/migrations/0026_merge.py
djangocms_blog/migrations/0027_post_date_featured.py
djangocms_blog/migrations/0028_auto_20170304_1040.py
djangocms_blog/migrations/0029_post_related.py
djangocms_blog/migrations/0030_auto_20170509_1831.py
djangocms_blog/migrations/0031_auto_20170610_1744.py
djangocms_blog/migrations/0032_auto_20180109_0023.py
djangocms_stories-0.7.6.dist-info/licenses/LICENSE
djangocms_stories-0.7.6.dist-info/METADATA
djangocms_stories-0.7.6.dist-info/WHEEL
djangocms_stories-0.7.6.dist-info/top_level.txt
djangocms_stories-0.7.6.dist-info/RECORD
