Metadata-Version: 2.4
Name: djangocms-stories
Version: 0.7.6
Summary: The versatile stories and blog application for django CMS 4+
Author-email: Fabian Braun <fsbraun@gmx.de>
License-Expression: BSD-3-Clause
Project-URL: Homepage, https://github.com/django-cms/djangocms-stories
Project-URL: Issues, https://github.com/fsbraun/djangocms-stories/issues
Classifier: Development Status :: 5 - Production/Stable
Classifier: Framework :: Django
Classifier: Framework :: Django :: 4.2
Classifier: Framework :: Django :: 5.0
Classifier: Framework :: Django :: 5.1
Classifier: Framework :: Django :: 5.2
Classifier: Framework :: Django CMS :: 4.1
Classifier: Framework :: Django CMS :: 5.0
Classifier: Programming Language :: Python :: 3 :: Only
Classifier: Programming Language :: Python :: 3.10
Classifier: Programming Language :: Python :: 3.11
Classifier: Programming Language :: Python :: 3.12
Classifier: Programming Language :: Python :: 3.13
Requires-Python: >=3.10
License-File: LICENSE
Requires-Dist: django-cms>=4.1
Requires-Dist: django-filer>=2
Requires-Dist: django-meta>=2
Requires-Dist: django-parler>=2
Requires-Dist: django-sortedm2m
Requires-Dist: django-taggit>=1
Requires-Dist: django-taggit-autosuggest
Requires-Dist: django-taggit-templatetags
Requires-Dist: easy-thumbnails>=2.4.1
Requires-Dist: lxml
Requires-Dist: pytz
Provides-Extra: docs
Requires-Dist: django<5; extra == "docs"
Provides-Extra: taggit-helpers
Requires-Dist: django-taggit-helpers; extra == "taggit-helpers"
Provides-Extra: test
Requires-Dist: coverage; extra == "test"
Requires-Dist: coveralls>=2; extra == "test"
Requires-Dist: django-taggit-helpers; extra == "test"
Requires-Dist: djangocms-text; extra == "test"
Requires-Dist: djangocms-video; extra == "test"
Requires-Dist: pysolr; extra == "test"
Requires-Dist: pytest; extra == "test"
Requires-Dist: pytest-asyncio; extra == "test"
Requires-Dist: pytest-django; extra == "test"
Dynamic: license-file
